esx_cli/ESX.py
esx_cli/__init__.py
esx_cli/cli.py
esx_cli-0.2.dist-info/DESCRIPTION.rst
esx_cli-0.2.dist-info/METADATA
esx_cli-0.2.dist-info/RECORD
esx_cli-0.2.dist-info/WHEEL
esx_cli-0.2.dist-info/entry_points.txt
esx_cli-0.2.dist-info/metadata.json
esx_cli-0.2.dist-info/top_level.txt
