Metadata-Version: 2.0
Name: esx-cli
Version: 0.2
Summary: A command line tool for managing vCenter and ESXi servers
Home-page: http://github.com/Moshe-Immerman/esx-cli
Author: Moshe Immerman
Author-email: name.surname@gmail.com
License: BSD
Platform: any
Requires-Dist: Click
Requires-Dist: paramiko
Requires-Dist: pyvmomi
Requires-Dist: requests
Requires-Dist: sh
